AUTHORS
COPYING
INSTALL
LICENSE
MANIFEST.in
README.rst
changes.rst
requirements-dev.txt
setup.cfg
setup.py
iocapture/__init__.py
iocapture.egg-info/PKG-INFO
iocapture.egg-info/SOURCES.txt
iocapture.egg-info/dependency_links.txt
iocapture.egg-info/not-zip-safe
iocapture.egg-info/top_level.txt