Metadata-Version: 1.1
Name: iocapture
Version: 0.1.2
Summary: Capture stdout, stderr easily.
Home-page: https://github.com/oinume/iocapture
Author: Kazuhiro Oinuma
Author-email: oinume@gmail.com
License: MIT
Platform: unix
Classifier: Development Status :: 5 - Production/Stable
Classifier: License :: OSI Approved :: MIT License
Classifier: Operating System :: OS Independent
Classifier: Programming Language :: Python
Classifier: Programming Language :: Python :: 2.4
Classifier: Programming Language :: Python :: 2.5
Classifier: Programming Language :: Python :: 2.6
Classifier: Programming Language :: Python :: 2.7
Classifier: Programming Language :: Python :: 3
Classifier: Programming Language :: Python :: 3.2
Classifier: Programming Language :: Python :: 3.3
Classifier: Topic :: Software Development :: Libraries :: Python Modules
